antotate/__init__.py
antotate/antotate.py
antotate-0.0.1.data/scripts/example.py
antotate-0.0.1.dist-info/LICENSE
antotate-0.0.1.dist-info/METADATA
antotate-0.0.1.dist-info/WHEEL
antotate-0.0.1.dist-info/top_level.txt
antotate-0.0.1.dist-info/RECORD
