Metadata-Version: 2.2
Name: antotate
Version: 0.0.1
Summary: Antotate is a tool allowing for the automatic annotation of Antimony files.
Home-page: https://github.com/mkcook/antotate
Author: Margaret Cook
Author-email: mkcook@uw.edu
Project-URL: Bug Tracker, https://github.com/mkcook/antotate/issues
Classifier: Programming Language :: Python :: 3
Classifier: License :: OSI Approved :: MIT License
Classifier: Operating System :: OS Independent
Requires-Python: >=3.9
License-File: LICENSE
Requires-Dist: tellurium>=2.2.10
Requires-Dist: bioservices>=1.12.0
Requires-Dist: equilibrator-api>=0.6.0
Dynamic: author
Dynamic: author-email
Dynamic: classifier
Dynamic: description
Dynamic: description-content-type
Dynamic: home-page
Dynamic: project-url
Dynamic: requires-dist
Dynamic: requires-python
Dynamic: summary
